modules/advanced_parameters.py
modules/anisotropic.py
modules/async_worker.py
modules/auth.py
modules/config.py
modules/constants.py
modules/core.py
modules/default_pipeline.py
modules/flags.py
modules/gradio_hijack.py
modules/html.py
modules/inpaint_worker.py
modules/launch_util.py
modules/localization.py
modules/lora.py
modules/meta_parser.py
modules/model_loader.py
modules/patch.py
modules/patch_clip.py
modules/patch_precision.py
modules/private_logger.py
modules/sample_hijack.py
modules/sdxl_styles.py
modules/style_sorter.py
modules/ui_gradio_extensions.py
modules/upscaler.py
modules/util.py
fooocus-0.1.1.dist-info/LICENSE
fooocus-0.1.1.dist-info/METADATA
fooocus-0.1.1.dist-info/WHEEL
fooocus-0.1.1.dist-info/RECORD
